{
  "ts": "2025-11-23T21:43:15.546640Z",
  "ts_ms": 1763934195546,
  "tag": "speedtest",
  "latest_report": {
    "score": {
      "wifi_health_score": 100,
      "explanation": "Your Wi-Fi network is operating optimally with no significant congestion.",
      "trend": {
        "download_delta_mbps": 96.2,
        "upload_delta_mbps": 21.84,
        "ping_delta_ms": 23.46,
        "networks_delta": -3
      },
      "trend_summary": "Since last scan: download improved, upload improved, ping improved, networks decreased."
    },
    "diagnosis": "Your network has excellent performance, but experiences random dropouts, likely due to signal interference or router placement.",
    "performance": {
      "download_mbps": 96.2,
      "upload_mbps": 21.84,
      "ping_ms": 23.46,
      "interpretation": "The download and upload speeds are approaching your ISP's max capacity, ensuring satisfactory performance for most activities."
    },
    "problems": [
      "Random dropouts potentially caused by interference from neighboring networks.",
      "Router placement near a window may lead to signal loss.",
      "Single frequency bands might not optimize device allocation."
    ],
    "fixes": [
      "Change the 2.4GHz channel to 6 to minimize interference from neighboring networks.",
      "Change the 5GHz channel to 149 for optimal performance since channels 36 are crowded.",
      "Consider relocating the router away from the bedroom window to improve coverage."
    ],
    "router_steps": "N/A",
    "questions": []
  },
  "wifi_scan": {
    "ts": 1763934173.7099662,
    "platform": "darwin",
    "networks": [
      {
        "ssid": "DIRECT-69-HP DeskJet 2800 series",
        "channel": "6 (2GHz, 20MHz)",
        "phymode": "802.11g/n",
        "security": "spairport_security_mode_wpa2_personal",
        "rssi_dbm": -92,
        "noise_dbm": -94
      },
      {
        "ssid": "Home1",
        "channel": "36 (5GHz, 80MHz)",
        "phymode": "802.11a/n/ac",
        "security": "spairport_security_mode_wpa2_personal",
        "rssi_dbm": -60,
        "noise_dbm": -92
      },
      {
        "ssid": "Home1",
        "channel": "11 (2GHz, 20MHz)",
        "phymode": "802.11b/g/n",
        "security": "spairport_security_mode_wpa2_personal",
        "rssi_dbm": -55,
        "noise_dbm": -94
      },
      {
        "ssid": "Xfinity Mobile",
        "channel": "36 (5GHz, 80MHz)",
        "phymode": "802.11a/n/ac",
        "security": "spairport_security_mode_wpa2_enterprise",
        "rssi_dbm": -79,
        "noise_dbm": -92
      },
      {
        "ssid": "adamel151",
        "channel": "1 (2GHz, 20MHz)",
        "phymode": "802.11g/n/ax",
        "security": "spairport_security_mode_wpa2_personal",
        "rssi_dbm": -71,
        "noise_dbm": -94
      },
      {
        "ssid": "adamel151",
        "channel": "157 (5GHz, 80MHz)",
        "phymode": "802.11a/n/ac/ax",
        "security": "spairport_security_mode_wpa2_personal",
        "rssi_dbm": -88,
        "noise_dbm": -92
      },
      {
        "ssid": "xfinitywifi",
        "channel": "36 (5GHz, 80MHz)",
        "phymode": "802.11a/n/ac",
        "security": "spairport_security_mode_none",
        "rssi_dbm": -61,
        "noise_dbm": -92
      }
    ],
    "speedtest": {
      "download_mbps": 83.16,
      "upload_mbps": 23.47,
      "ping_ms": 36.76,
      "method": "python-speedtest"
    }
  }
}